mactoast/__init__.py
mactoast/_runner.py
mactoast/py.typed
mactoast/styles.py
mactoast/ToastHUD.app/Contents/Info.plist
mactoast/ToastHUD.app/Contents/PkgInfo
mactoast/ToastHUD.app/Contents/MacOS/ToastHUD
mactoast/ToastHUD.app/Contents/Resources/beep1.wav
mactoast/ToastHUD.app/Contents/Resources/beep2.wav
mactoast/ToastHUD.app/Contents/Resources/beep3.wav
mactoast/ToastHUD.app/Contents/Resources/beep4.m4a
mactoast/ToastHUD.app/Contents/Resources/beep5.m4a
mactoast/ToastHUD.app/Contents/Resources/click1.wav
mactoast/ToastHUD.app/Contents/Resources/confirmation1.wav
mactoast/ToastHUD.app/Contents/Resources/confirmation2.wav
mactoast/ToastHUD.app/Contents/Resources/confirmation3.wav
mactoast/ToastHUD.app/Contents/Resources/confirmation4.m4a
mactoast/ToastHUD.app/Contents/Resources/confirmation5.wav
mactoast/ToastHUD.app/Contents/Resources/pop1.mp3
mactoast/ToastHUD.app/Contents/Resources/pop2.wav
mactoast/ToastHUD.app/Contents/Resources/pop3.wav
mactoast/ToastHUD.app/Contents/Resources/scifi1.m4a
mactoast/ToastHUD.app/Contents/Resources/scifi2.wav
mactoast/ToastHUD.app/Contents/Resources/scifi3.wav
mactoast/ToastHUD.app/Contents/_CodeSignature/CodeResources
mactoast-0.1.1.dist-info/METADATA
mactoast-0.1.1.dist-info/WHEEL
mactoast-0.1.1.dist-info/licenses/LICENSE
mactoast-0.1.1.dist-info/RECORD
