Metadata-Version: 2.4
Name: mactoast
Version: 0.1.1
Summary: Easy, elegant and customizable toast notifications for macOS with icons, sounds, and more.
Project-URL: Homepage, https://github.com/rafa-rrayes/mactoast
Project-URL: Repository, https://github.com/rafa-rrayes/mactoast
Project-URL: Documentation, https://github.com/rafa-rrayes/mactoast/blob/master/DOCS.md
Project-URL: Bug Reports, https://github.com/rafa-rrayes/mactoast/issues
Project-URL: Changelog, https://github.com/rafa-rrayes/mactoast/blob/master/CHANGELOG.md
Author-email: rafa-rrayes <rafa@rayes.com.br>
License: MIT
License-File: LICENSE
Keywords: alert,gui,macos,native,notification,popup,swift,toast
Classifier: Development Status :: 4 - Beta
Classifier: Intended Audience :: Developers
Classifier: License :: OSI Approved :: MIT License
Classifier: Operating System :: MacOS :: MacOS X
Classifier: Programming Language :: Python :: 3
Classifier: Programming Language :: Python :: 3.8
Classifier: Programming Language :: Python :: 3.9
Classifier: Programming Language :: Python :: 3.10
Classifier: Programming Language :: Python :: 3.11
Classifier: Programming Language :: Python :: 3.12
Classifier: Programming Language :: Python :: 3.13
Classifier: Topic :: Desktop Environment
Classifier: Topic :: Software Development :: Libraries :: Python Modules
Requires-Python: >=3.8
